visionner/__init__.py
visionner/core.py
visionner-0.0.7.dist-info/METADATA
visionner-0.0.7.dist-info/WHEEL
visionner-0.0.7.dist-info/top_level.txt
visionner-0.0.7.dist-info/RECORD
