Metadata-Version: 2.1
Name: visionner
Version: 0.0.7
Summary: Turn raw image dataset into numpy array ; more suitable for deep learning tasks
Home-page: https://github.com/charleslf2/visionner
Author: charles TCHANAKE
Author-email: datadevfernolf@gmail.com
Keywords: Computer-vision,preprocessing,Images,Dataset,visionner
Classifier: Development Status :: 3 - Alpha
Classifier: Programming Language :: Python :: 3
Classifier: Operating System :: MacOS :: MacOS X
Classifier: Operating System :: Microsoft :: Windows
Requires-Dist: numpy
Requires-Dist: opencv-python
Requires-Dist: matplotlib
Requires-Dist: rich
